cmlattice/__init__.py
cmlattice/cli.py
cmlattice/cmlattice.py
cmlattice/kaneko.py
cmlattice/rulkov.py
cmlattice/viz.py
cmlattice-0.0.3.dist-info/METADATA
cmlattice-0.0.3.dist-info/WHEEL
cmlattice-0.0.3.dist-info/entry_points.txt
cmlattice-0.0.3.dist-info/RECORD
