Metadata-Version: 2.4
Name: cmlattice
Version: 0.0.3
Summary: An implementation of coupled map lattices.
Requires-Python: >=3.13
Requires-Dist: matplotlib>=3.10.1
Requires-Dist: numpy>=2.2.5
